teamup_connect/__init__.py
teamup_connect/teamup_api.py
teamup_connect-0.3.0.dist-info/METADATA
teamup_connect-0.3.0.dist-info/WHEEL
teamup_connect-0.3.0.dist-info/top_level.txt
teamup_connect-0.3.0.dist-info/RECORD
