Metadata-Version: 2.1
Name: teamup_connect
Version: 0.3.0
Summary: A package designed to facilitate easy interaction with TeamUp API.
Author-email: Tony <cordial.egg1739@fastmail.com>
License: MIT
Keywords: one,two
Classifier: Programming Language :: Python :: 3
Requires-Python: >=3.10
Requires-Dist: requests
Requires-Dist: python-dotenv
Requires-Dist: importlib-metadata; python_version < "3.10"
Provides-Extra: dev
Requires-Dist: py-teamup[release,static-code-qa,test]; extra == "dev"
Provides-Extra: release
Requires-Dist: build; extra == "release"
Requires-Dist: twine; extra == "release"
Provides-Extra: static-code-qa
Requires-Dist: pre-commit; extra == "static-code-qa"
Provides-Extra: test
Requires-Dist: pytest; extra == "test"
Requires-Dist: pytest-cov; extra == "test"
